{
    "01": {
        "en": "Pinar del Río",
        "hi": "पिनार डेल रियो",
        "ka": "პინარ-დელ-რიო",
        "ru": "Пинар-дель-Рио",
        "ta": "பினார் டெல் ரியோ",
        "uk": "Пінар-дель-Ріо"
    },
    "03": {
        "en": "La Habana",
        "be": "Горад Гавана",
        "eo": "Havano",
        "ga": "Havana",
        "hi": "ला हबाना",
        "hu": "Havanna",
        "it": "L'Avana",
        "ka": "ლა ჰაბანა",
        "pl": "Hawana",
        "ru": "Гавана",
        "sc": "S'Avana",
        "sl": "Havana",
        "sr": "Ла Хавана",
        "sv": "Havanna",
        "ta": "லா உபானா",
        "th": "ลาอาบานา",
        "uk": "Гавана"
    },
    "04": {
        "en": "Matanzas",
        "be": "Матансас",
        "hi": "मेटांज़ाज",
        "ja": "マタンサス",
        "ka": "მატანსასი",
        "ru": "Матансас",
        "sr": "Матанзас",
        "ta": "மாடன்சாச்",
        "th": "มาตันซัส",
        "uk": "Матанзас"
    },
    "05": {
        "en": "Villa Clara",
        "be": "Вілья-Клара",
        "hi": "विला क्लारा",
        "id": "c",
        "ja": "ビヤクララ",
        "ka": "ვილია კლარა",
        "sr": "Вила Клара",
        "ta": "வில்லா கிளாரா",
        "uk": "Клара"
    },
    "06": {
        "en": "Cienfuegos",
        "be": "Сьенфуэгас",
        "eo": "Cienfajrio",
        "hi": "सिएनफ़्यूगोस",
        "ja": "シエンフエゴス",
        "ka": "სიენფუეგოსი",
        "ru": "Сьенфуэгос",
        "sr": "Сјенфуегос",
        "ta": "சியென்ஃபுகோச்",
        "th": "เซียนฟวยโกส",
        "uk": "Сьєнфуегос"
    },
    "07": {
        "en": "Sancti Spíritus",
        "be": "Санкты-Спірытус",
        "eo": "Sankta Spirito",
        "fr": "Sancti Spiritus",
        "hi": "सैंक्टी स्पिरिटस",
        "it": "Sancti Spiritus",
        "ja": "サンクティスピリトゥス",
        "ka": "სანქტი-სპირიტუსი",
        "ru": "Санкти-Спиритус",
        "sc": "Sancti Spìritus",
        "sl": "Sancti Spiritus",
        "ta": "சான்கி ச்பிரிட்டச்",
        "th": "ซังก์ตีสปีรีตุส",
        "uk": "Санкті-Спіритус"
    },
    "08": {
        "en": "Ciego de Ávila",
        "be": "Сьега-дэ-Авіла",
        "fr": "Ciego de Avila",
        "hi": "सिएगो डे एविला",
        "it": "Ciego de Avila",
        "ja": "シエゴデアビラ",
        "ka": "სიეგო-დე-ავილა",
        "ru": "Сьего-де-Авила",
        "sc": "Ciego de Àvila",
        "sl": "Ciego de Avila",
        "sr": "Сјего де Авила",
        "ta": "CIEGO DE ávila",
        "uk": "Сьєго-де-Авіла"
    },
    "09": {
        "en": "Camagüey",
        "be": "Камагуэй",
        "ga": "Camaguey",
        "hi": "कैमागुए",
        "it": "Camaguey",
        "ja": "カマグエイ",
        "ka": "კამაგუეი",
        "ru": "Камагуэй",
        "sc": "Camaguey",
        "sl": "Camaguey",
        "sr": "Камагиј",
        "ta": "Camagசி",
        "th": "กามากูเอย์",
        "uk": "Камагуей"
    },
    "10": {
        "en": "Las Tunas",
        "be": "Лас-Тунас",
        "ga": "Las Tuinníní",
        "hi": "लास टुनस",
        "ja": "ラストゥーナス",
        "ka": "ლას-ტუნასი",
        "sc": "Sas Tunas",
        "sr": "Лас Тунас",
        "ta": "லாச் துனாச்",
        "uk": "Лас-Тунас"
    },
    "11": {
        "en": "Holguín",
        "be": "Ольгін",
        "da": "Holguin",
        "fr": "Holguin",
        "hi": "होल्गुइन",
        "it": "Holguin",
        "ja": "オルギン",
        "ka": "ოლგინი",
        "ru": "Ольгин",
        "sc": "Holguìn",
        "sr": "Холгвин",
        "ta": "ஓல்குன்",
        "th": "ออลกีน",
        "uk": "Ольгін"
    },
    "12": {
        "en": "Granma",
        "be": "Гранма",
        "hi": "ग्रानमा",
        "ja": "グランマ",
        "ka": "გრანმა",
        "ru": "Гранма",
        "sr": "Гранма",
        "ta": "கிரான்மா",
        "uk": "Гранма"
    },
    "13": {
        "en": "Santiago de Cuba",
        "be": "Сант'яга-дэ-Куба",
        "bg": "Сантяго де Куба",
        "eo": "Santiago de Kubo",
        "ga": "Santiago de Cúba",
        "hi": "सैंटियागो डे क्यूबा",
        "it": "Santiago di Cuba",
        "ja": "サンティアゴデクーバ",
        "ka": "სანტიაგო დე კუბა",
        "ru": "Сантьяго-де-Куба",
        "sr": "Сантјаго на Куби",
        "ta": "சாண்டியாகோ டி கியூபா",
        "th": "ซานเตียโกเดกูบา",
        "uk": "Сантьяго-де-Куба"
    },
    "14": {
        "en": "Guantánamo",
        "be": "Гуантанама",
        "da": "Guantanamo",
        "fr": "Guantanamo",
        "ga": "Guantanamo",
        "hi": "गुआंटानामो",
        "it": "Guantanamo",
        "ja": "グアンタナモ",
        "ka": "გუანტანამო",
        "lt": "Guantanamas",
        "ru": "Гуантанамо",
        "sc": "Guantànamo",
        "sl": "Guantanamo",
        "sr": "Гвантанамо",
        "ta": "குவாண்டநாமோ",
        "th": "กวานตานาโม",
        "uk": "Гуантанамо"
    },
    "15": {
        "en": "Artemisa",
        "eo": "Artemiso",
        "ga": "Mugwort",
        "hi": "आर्टेमिसा",
        "ka": "არტემისა",
        "ru": "Артемиса",
        "ta": "ஆர்ட்டெமிசா",
        "uk": "Артеміса"
    },
    "16": {
        "en": "Mayabeque",
        "hi": "मायाबेक्यू",
        "ka": "მაიაბეკე",
        "ta": "மாயாபெக்",
        "uk": "Маябеке"
    }
}