{
    "AN": {
        "en": "Ansabā",
        "ba": "Ансэба",
        "be": "Ансеба",
        "de": "Anseba",
        "ga": "Ansaba",
        "he": "אנסבה",
        "hi": "अंसबा",
        "it": "Regione dell'Anseba",
        "lo": "ອັນຊາບາ",
        "nl": "Anseba",
        "pl": "Anseba",
        "ro": "Anseba",
        "sc": "Anseba",
        "ta": "அன்சாபா",
        "uk": "Ансеба"
    },
    "DK": {
        "en": "Janūbī al Baḩrī al Aḩmar",
        "ga": "Muir Rua Theas",
        "lo": "ຈານູບີ ອັນ ບາຣີ ອັນ ອາມາ",
        "ro": "Debubawi Keyih Bahri (Marea Roșie de Sud)",
        "uk": "Дженупі аль-Бахрі аль-Ахмар"
    },
    "DU": {
        "en": "Al Janūbī",
        "ba": "Көньяҡ",
        "be": "Паўднёвы рэгіён",
        "he": "הדרום",
        "hi": "अल जनुबी",
        "it": "Regione del Sud",
        "lo": "ອັນ ຈານູບີ",
        "nl": "Debub",
        "pl": "Region Południowy",
        "ro": "Debub (Sudică)",
        "sc": "Regione de su Sud",
        "sv": "Debubregionen",
        "ta": "அல் சானபே",
        "tr": "Al Janubi",
        "uk": "Південна"
    },
    "GB": {
        "en": "Qāsh-Barkah",
        "lo": "ກາສ-ບາກະ",
        "ro": "Gash-Barka",
        "uk": "Каш-Барка"
    },
    "MA": {
        "en": "Al Awsaţ",
        "ba": "Үҙәк",
        "be": "Цэнтральны рэгіён",
        "he": "המרכז",
        "hi": "अल औसत",
        "it": "Regione centrale",
        "lo": "ອັນ ອາວຊັດ",
        "nl": "Maekel",
        "pl": "Region Centralny",
        "ro": "Maekel (Centrală)",
        "sc": "Regione tzentrale",
        "sr": "Ал Авсат",
        "ta": "Al awsaţ",
        "uk": "Східна"
    },
    "SK": {
        "en": "Shimālī al Baḩrī al Aḩmar",
        "ga": "Muir Thuaidh Muir Rua",
        "lo": "ຊິມາລີ ອັນ ບາຣີ ອັນ ອາມາ",
        "ro": "Semien-Keih-Bahri",
        "uk": "Шімалі аль-Бахрі аль-Ахмар"
    }
}