{
    "A": {
        "en": "Anjouan",
        "hi": "ऐंजुआन",
        "ro": "Insula Anjouan",
        "ta": "அஞ்சோவன்",
        "uk": "Анжуан"
    },
    "G": {
        "en": "Grande Comore",
        "ga": "Comoros Mór",
        "hi": "ग्रांडे कोमोर",
        "hu": "Nagy-Komoró",
        "pl": "Wielki Komor",
        "ro": "Insula Grande Comore",
        "ta": "கிராண்டே கோமோர்",
        "uk": "Великий Комор"
    },
    "M": {
        "en": "Mohéli",
        "hi": "मोहेली",
        "ro": "Insula Mohéli",
        "ta": "மொஎலி",
        "uk": "Мохелі"
    }
}