{
    "01": {
        "en_US": "Johor",
        "be": "Джахор",
        "be_BY": "Джахор",
        "hi": "जोहोर",
        "hi_IN": "जोहोर",
        "ja": "ジョホール",
        "ja_JP": "ジョホール",
        "ka": "ჯოჰორი",
        "ka_GE": "ჯოჰორი",
        "lt": "Džohoro sultonatas",
        "lt_LT": "Džohoro sultonatas",
        "sr": "Џохор",
        "sr@latin": "Džohor",
        "sr_Cyrl": "Џохор",
        "sr_Cyrl_BA": "Џохор",
        "sr_Cyrl_ME": "Џохор",
        "sr_Cyrl_RS": "Џохор",
        "sr_Cyrl_XK": "Џохор",
        "ta": "சொஓர்",
        "ta_IN": "சொஓர்",
        "ta_LK": "சொஓர்",
        "ta_MY": "சொஓர்",
        "ta_SG": "சொஓர்",
        "th": "ยะโฮร์",
        "th_TH": "ยะโฮร์",
        "uk": "Джохор",
        "uk_UA": "Джохор"
    },
    "02": {
        "en_US": "Kedah",
        "be": "Кедах",
        "be_BY": "Кедах",
        "ga": "KedahGeneric",
        "ga_GB": "KedahGeneric",
        "ga_IE": "KedahGeneric",
        "hi": "केदाह",
        "hi_IN": "केदाह",
        "ka": "კედაჰი",
        "ka_GE": "კედაჰი",
        "lt": "Kedaho sultonatas",
        "lt_LT": "Kedaho sultonatas",
        "sr": "Кедах",
        "sr_Cyrl": "Кедах",
        "sr_Cyrl_BA": "Кедах",
        "sr_Cyrl_ME": "Кедах",
        "sr_Cyrl_RS": "Кедах",
        "sr_Cyrl_XK": "Кедах",
        "ta": "கெடா",
        "ta_IN": "கெடா",
        "ta_LK": "கெடா",
        "ta_MY": "கெடா",
        "ta_SG": "கெடா",
        "th": "เกดะห์",
        "th_TH": "เกดะห์",
        "uk": "Кедах",
        "uk_UA": "Кедах"
    },
    "03": {
        "en_US": "Kelantan",
        "be": "Келантан",
        "be_BY": "Келантан",
        "hi": "केलान्टान",
        "hi_IN": "केलान्टान",
        "ja": "クランタン",
        "ja_JP": "クランタン",
        "ka": "კელანტანი",
        "ka_GE": "კელანტანი",
        "lt": "Kelantano sultonatas",
        "lt_LT": "Kelantano sultonatas",
        "sr": "Келантан",
        "sr_Cyrl": "Келантан",
        "sr_Cyrl_BA": "Келантан",
        "sr_Cyrl_ME": "Келантан",
        "sr_Cyrl_RS": "Келантан",
        "sr_Cyrl_XK": "Келантан",
        "ta": "கெலந்தன்",
        "ta_IN": "கெலந்தன்",
        "ta_LK": "கெலந்தன்",
        "ta_MY": "கெலந்தன்",
        "ta_SG": "கெலந்தன்",
        "th": "กลันตัน",
        "th_TH": "กลันตัน",
        "uk": "Келантан",
        "uk_UA": "Келантан"
    },
    "04": {
        "en_US": "Melaka",
        "be": "Малака",
        "be_BY": "Малака",
        "de": "Malakka",
        "de_AT": "Malakka",
        "de_BE": "Malakka",
        "de_CH": "Malakka",
        "de_DE": "Malakka",
        "de_IT": "Malakka",
        "de_LI": "Malakka",
        "de_LU": "Malakka",
        "eo": "Malako",
        "eo_001": "Malako",
        "hi": "मेलाका",
        "hi_IN": "मेलाका",
        "hu": "Malakka",
        "hu_HU": "Malakka",
        "ka": "მელაკა",
        "ka_GE": "მელაკა",
        "lt": "Malaka",
        "lt_LT": "Malaka",
        "nl": "Malakka; Melaka",
        "nl_AW": "Malakka; Melaka",
        "nl_BE": "Malakka; Melaka",
        "nl_BQ": "Malakka; Melaka",
        "nl_CW": "Malakka; Melaka",
        "nl_NL": "Malakka; Melaka",
        "nl_SR": "Malakka; Melaka",
        "nl_SX": "Malakka; Melaka",
        "pl": "Malakka",
        "pl_PL": "Malakka",
        "sr": "Мелака",
        "sr_Cyrl": "Мелака",
        "sr_Cyrl_BA": "Мелака",
        "sr_Cyrl_ME": "Мелака",
        "sr_Cyrl_RS": "Мелака",
        "sr_Cyrl_XK": "Мелака",
        "ta": "மெலகா",
        "ta_IN": "மெலகா",
        "ta_LK": "மெலகா",
        "ta_MY": "மெலகா",
        "ta_SG": "மெலகா",
        "th": "มะละกา",
        "th_TH": "มะละกา",
        "uk": "Мелака",
        "uk_UA": "Мелака"
    },
    "05": {
        "en_US": "Negeri Sembilan",
        "be": "Нігеры-Сембелан",
        "be_BY": "Нігеры-Сембелан",
        "hi": "नेगेरी सेम्बिलन",
        "hi_IN": "नेगेरी सेम्बिलन",
        "ja": "ヌグリスンビラン",
        "ja_JP": "ヌグリスンビラン",
        "ka": "ნეგერი სემბილანი",
        "ka_GE": "ნეგერი სემბილანი",
        "lt": "Negeri Sembilano monarchija",
        "lt_LT": "Negeri Sembilano monarchija",
        "ta": "நெகேரி செம்பிலன்",
        "ta_IN": "நெகேரி செம்பிலன்",
        "ta_LK": "நெகேரி செம்பிலன்",
        "ta_MY": "நெகேரி செம்பிலன்",
        "ta_SG": "நெகேரி செம்பிலன்",
        "th": "เนกรีเซมบีลัน",
        "th_TH": "เนกรีเซมบีลัน",
        "uk": "Негері-Сембелан",
        "uk_UA": "Негері-Сембелан"
    },
    "06": {
        "en_US": "Pahang",
        "be": "Паханг",
        "be_BY": "Паханг",
        "hi": "पहांग",
        "hi_IN": "पहांग",
        "ja": "パハン",
        "ja_JP": "パハン",
        "ka": "პაჰანგი",
        "ka_GE": "პაჰანგი",
        "lt": "Pahango sultonatas",
        "lt_LT": "Pahango sultonatas",
        "sr": "Паханг",
        "sr_Cyrl": "Паханг",
        "sr_Cyrl_BA": "Паханг",
        "sr_Cyrl_ME": "Паханг",
        "sr_Cyrl_RS": "Паханг",
        "sr_Cyrl_XK": "Паханг",
        "ta": "பஉாங்",
        "ta_IN": "பஉாங்",
        "ta_LK": "பஉாங்",
        "ta_MY": "பஉாங்",
        "ta_SG": "பஉாங்",
        "th": "ปะหัง",
        "th_TH": "ปะหัง",
        "uk": "Паханг",
        "uk_UA": "Паханг"
    },
    "07": {
        "en_US": "Pulau Pinang",
        "be": "Пулаў-Пінанг",
        "be_BY": "Пулаў-Пінанг",
        "de": "Penang",
        "de_AT": "Penang",
        "de_BE": "Penang",
        "de_CH": "Penang",
        "de_DE": "Penang",
        "de_IT": "Penang",
        "de_LI": "Penang",
        "de_LU": "Penang",
        "hi": "पुलाऊ पिनांग",
        "hi_IN": "पुलाऊ पिनांग",
        "hu": "Penang",
        "hu_HU": "Penang",
        "lt": "Penangas",
        "lt_LT": "Penangas",
        "nl": "Penang; Pulau Pinang",
        "nl_AW": "Penang; Pulau Pinang",
        "nl_BE": "Penang; Pulau Pinang",
        "nl_BQ": "Penang; Pulau Pinang",
        "nl_CW": "Penang; Pulau Pinang",
        "nl_NL": "Penang; Pulau Pinang",
        "nl_SR": "Penang; Pulau Pinang",
        "nl_SX": "Penang; Pulau Pinang",
        "pl": "Penang",
        "pl_PL": "Penang",
        "ta": "புலாவ் பினாங்",
        "ta_IN": "புலாவ் பினாங்",
        "ta_LK": "புலாவ் பினாங்",
        "ta_MY": "புலாவ் பினாங்",
        "ta_SG": "புலாவ் பினாங்",
        "th": "ปีนัง",
        "th_TH": "ปีนัง",
        "uk": "Пулау Пінанг",
        "uk_UA": "Пулау Пінанг"
    },
    "08": {
        "en_US": "Perak",
        "be": "Перак",
        "be_BY": "Перак",
        "hi": "पेराक",
        "hi_IN": "पेराक",
        "ka": "პერაკი",
        "ka_GE": "პერაკი",
        "lt": "Perakas",
        "lt_LT": "Perakas",
        "sr": "Перак",
        "sr_Cyrl": "Перак",
        "sr_Cyrl_BA": "Перак",
        "sr_Cyrl_ME": "Перак",
        "sr_Cyrl_RS": "Перак",
        "sr_Cyrl_XK": "Перак",
        "ta": "பெராக்",
        "ta_IN": "பெராக்",
        "ta_LK": "பெராக்",
        "ta_MY": "பெராக்",
        "ta_SG": "பெராக்",
        "th": "เประ",
        "th_TH": "เประ",
        "uk": "Перак",
        "uk_UA": "Перак"
    },
    "09": {
        "en_US": "Perlis",
        "be": "Перліс",
        "be_BY": "Перліс",
        "hi": "पर्लिस",
        "hi_IN": "पर्लिस",
        "ja": "ペルリス",
        "ja_JP": "ペルリス",
        "ka": "პერლისი",
        "ka_GE": "პერლისი",
        "lt": "Perlisas",
        "lt_LT": "Perlisas",
        "sr": "Перлис",
        "sr_Cyrl": "Перлис",
        "sr_Cyrl_BA": "Перлис",
        "sr_Cyrl_ME": "Перлис",
        "sr_Cyrl_RS": "Перлис",
        "sr_Cyrl_XK": "Перлис",
        "ta": "பெர்லிச்",
        "ta_IN": "பெர்லிச்",
        "ta_LK": "பெர்லிச்",
        "ta_MY": "பெர்லிச்",
        "ta_SG": "பெர்லிச்",
        "th": "ปะลิส",
        "th_TH": "ปะลิส",
        "uk": "Перліс",
        "uk_UA": "Перліс"
    },
    "10": {
        "en_US": "Selangor",
        "be": "Селангор",
        "be_BY": "Селангор",
        "hi": "सेलांगर",
        "hi_IN": "सेलांगर",
        "ja": "スランゴール",
        "ja_JP": "スランゴール",
        "ka": "სელანგორი",
        "ka_GE": "სელანგორი",
        "lt": "Selangoro sultonatas",
        "lt_LT": "Selangoro sultonatas",
        "sr": "Селангор",
        "sr_Cyrl": "Селангор",
        "sr_Cyrl_BA": "Селангор",
        "sr_Cyrl_ME": "Селангор",
        "sr_Cyrl_RS": "Селангор",
        "sr_Cyrl_XK": "Селангор",
        "ta": "சிலாங்கூர்",
        "ta_IN": "சிலாங்கூர்",
        "ta_LK": "சிலாங்கூர்",
        "ta_MY": "சிலாங்கூர்",
        "ta_SG": "சிலாங்கூர்",
        "th": "สลังงอร์",
        "th_TH": "สลังงอร์",
        "uk": "Селангор",
        "uk_UA": "Селангор"
    },
    "11": {
        "en_US": "Terengganu",
        "be": "Трэнгану",
        "be_BY": "Трэнгану",
        "hi": "तेरेंगानु",
        "hi_IN": "तेरेंगानु",
        "ja": "トレンガヌ",
        "ja_JP": "トレンガヌ",
        "ka": "ტრენგანუ",
        "ka_GE": "ტრენგანუ",
        "lt": "Terenganu sultonatas",
        "lt_LT": "Terenganu sultonatas",
        "ta": "டெரெங்கானு",
        "ta_IN": "டெரெங்கானு",
        "ta_LK": "டெரெங்கானு",
        "ta_MY": "டெரெங்கானு",
        "ta_SG": "டெரெங்கானு",
        "th": "ตรังกานู",
        "th_TH": "ตรังกานู",
        "uk": "Теренгану",
        "uk_UA": "Теренгану"
    },
    "12": {
        "en_US": "Sabah",
        "be": "Сабах",
        "be_BY": "Сабах",
        "ga": "Maidin",
        "ga_GB": "Maidin",
        "ga_IE": "Maidin",
        "hi": "सबा",
        "hi_IN": "सबा",
        "ja": "サバ",
        "ja_JP": "サバ",
        "ka": "საბაჰი",
        "ka_GE": "საბაჰი",
        "lt": "Sabahas",
        "lt_LT": "Sabahas",
        "sr": "Саба",
        "sr@latin": "Saba",
        "sr_Cyrl": "Саба",
        "sr_Cyrl_BA": "Саба",
        "sr_Cyrl_ME": "Саба",
        "sr_Cyrl_RS": "Саба",
        "sr_Cyrl_XK": "Саба",
        "ta": "சபா",
        "ta_IN": "சபா",
        "ta_LK": "சபா",
        "ta_MY": "சபா",
        "ta_SG": "சபா",
        "th": "ซาบาห์",
        "th_TH": "ซาบาห์",
        "uk": "Сабах",
        "uk_UA": "Сабах"
    },
    "13": {
        "en_US": "Sarawak",
        "be": "Саравак",
        "be_BY": "Саравак",
        "hi": "सरवाक",
        "hi_IN": "सरवाक",
        "ja": "サラワク",
        "ja_JP": "サラワク",
        "ka": "სარავაკი",
        "ka_GE": "სარავაკი",
        "lt": "Saravakas",
        "lt_LT": "Saravakas",
        "sr": "Саравак",
        "sr@latin": "Saravak",
        "sr_Cyrl": "Саравак",
        "sr_Cyrl_BA": "Саравак",
        "sr_Cyrl_ME": "Саравак",
        "sr_Cyrl_RS": "Саравак",
        "sr_Cyrl_XK": "Саравак",
        "ta": "சரவாக்",
        "ta_IN": "சரவாக்",
        "ta_LK": "சரவாக்",
        "ta_MY": "சரவாக்",
        "ta_SG": "சரவாக்",
        "th": "ซาราวัก",
        "th_TH": "ซาราวัก",
        "uk": "Саравак",
        "uk_UA": "Саравак"
    },
    "14": {
        "en_US": "Wilayah Persekutuan Kuala Lumpur",
        "be": "Фэдэральная тэрыторыя Куала-Лумпур",
        "be_BY": "Фэдэральная тэрыторыя Куала-Лумпур",
        "de": "Bundesterritorium Kuala Lumpur",
        "de_AT": "Bundesterritorium Kuala Lumpur",
        "de_BE": "Bundesterritorium Kuala Lumpur",
        "de_CH": "Bundesterritorium Kuala Lumpur",
        "de_DE": "Bundesterritorium Kuala Lumpur",
        "de_IT": "Bundesterritorium Kuala Lumpur",
        "de_LI": "Bundesterritorium Kuala Lumpur",
        "de_LU": "Bundesterritorium Kuala Lumpur",
        "eo": "Federacia Teritorio Kuala-Lumpuro",
        "eo_001": "Federacia Teritorio Kuala-Lumpuro",
        "fr": "Kuala Lumpur (territoire fédéral)",
        "fr_BE": "Kuala Lumpur (territoire fédéral)",
        "fr_BF": "Kuala Lumpur (territoire fédéral)",
        "fr_BI": "Kuala Lumpur (territoire fédéral)",
        "fr_BJ": "Kuala Lumpur (territoire fédéral)",
        "fr_BL": "Kuala Lumpur (territoire fédéral)",
        "fr_CA": "Kuala Lumpur (territoire fédéral)",
        "fr_CD": "Kuala Lumpur (territoire fédéral)",
        "fr_CF": "Kuala Lumpur (territoire fédéral)",
        "fr_CG": "Kuala Lumpur (territoire fédéral)",
        "fr_CH": "Kuala Lumpur (territoire fédéral)",
        "fr_CI": "Kuala Lumpur (territoire fédéral)",
        "fr_CM": "Kuala Lumpur (territoire fédéral)",
        "fr_DJ": "Kuala Lumpur (territoire fédéral)",
        "fr_DZ": "Kuala Lumpur (territoire fédéral)",
        "fr_FR": "Kuala Lumpur (territoire fédéral)",
        "fr_GA": "Kuala Lumpur (territoire fédéral)",
        "fr_GF": "Kuala Lumpur (territoire fédéral)",
        "fr_GN": "Kuala Lumpur (territoire fédéral)",
        "fr_GP": "Kuala Lumpur (territoire fédéral)",
        "fr_GQ": "Kuala Lumpur (territoire fédéral)",
        "fr_HT": "Kuala Lumpur (territoire fédéral)",
        "fr_KM": "Kuala Lumpur (territoire fédéral)",
        "fr_LU": "Kuala Lumpur (territoire fédéral)",
        "fr_MA": "Kuala Lumpur (territoire fédéral)",
        "fr_MC": "Kuala Lumpur (territoire fédéral)",
        "fr_MF": "Kuala Lumpur (territoire fédéral)",
        "fr_MG": "Kuala Lumpur (territoire fédéral)",
        "fr_ML": "Kuala Lumpur (territoire fédéral)",
        "fr_MQ": "Kuala Lumpur (territoire fédéral)",
        "fr_MR": "Kuala Lumpur (territoire fédéral)",
        "fr_MU": "Kuala Lumpur (territoire fédéral)",
        "fr_NC": "Kuala Lumpur (territoire fédéral)",
        "fr_NE": "Kuala Lumpur (territoire fédéral)",
        "fr_PF": "Kuala Lumpur (territoire fédéral)",
        "fr_PM": "Kuala Lumpur (territoire fédéral)",
        "fr_RE": "Kuala Lumpur (territoire fédéral)",
        "fr_RW": "Kuala Lumpur (territoire fédéral)",
        "fr_SC": "Kuala Lumpur (territoire fédéral)",
        "fr_SN": "Kuala Lumpur (territoire fédéral)",
        "fr_SY": "Kuala Lumpur (territoire fédéral)",
        "fr_TD": "Kuala Lumpur (territoire fédéral)",
        "fr_TG": "Kuala Lumpur (territoire fédéral)",
        "fr_TN": "Kuala Lumpur (territoire fédéral)",
        "fr_VU": "Kuala Lumpur (territoire fédéral)",
        "fr_WF": "Kuala Lumpur (territoire fédéral)",
        "fr_YT": "Kuala Lumpur (territoire fédéral)",
        "ga": "Críoch Chónaidhme Kuala Lumpur",
        "ga_GB": "Críoch Chónaidhme Kuala Lumpur",
        "ga_IE": "Críoch Chónaidhme Kuala Lumpur",
        "hi": "विलायह पर्सेकुटुआन कुआलालंपुर",
        "hi_IN": "विलायह पर्सेकुटुआन कुआलालंपुर",
        "hu": "Kuala Lumpur szövetségi terület",
        "hu_HU": "Kuala Lumpur szövetségi terület",
        "it": "Kuala Lumpur",
        "it_CH": "Kuala Lumpur",
        "it_IT": "Kuala Lumpur",
        "it_SM": "Kuala Lumpur",
        "it_VA": "Kuala Lumpur",
        "lt": "Kvala Lumpūro federalinė·teritorija",
        "lt_LT": "Kvala Lumpūro federalinė·teritorija",
        "nl": "Kuala Lumpur, Federaal Territorium",
        "nl_AW": "Kuala Lumpur, Federaal Territorium",
        "nl_BE": "Kuala Lumpur, Federaal Territorium",
        "nl_BQ": "Kuala Lumpur, Federaal Territorium",
        "nl_CW": "Kuala Lumpur, Federaal Territorium",
        "nl_NL": "Kuala Lumpur, Federaal Territorium",
        "nl_SR": "Kuala Lumpur, Federaal Territorium",
        "nl_SX": "Kuala Lumpur, Federaal Territorium",
        "pl": "Kuala Lumpur (terytorium federalne)",
        "pl_PL": "Kuala Lumpur (terytorium federalne)",
        "ro": "Teritoriul Federal Kuala Lumpur",
        "ro_MD": "Teritoriul Federal Kuala Lumpur",
        "ro_RO": "Teritoriul Federal Kuala Lumpur",
        "sv": "Kuala Lumpur (territorium)",
        "sv_AX": "Kuala Lumpur (territorium)",
        "sv_FI": "Kuala Lumpur (territorium)",
        "sv_SE": "Kuala Lumpur (territorium)",
        "ta": "விலயா பெர்செக்குட்டுவான் கோலாலம்பூர்",
        "ta_IN": "விலயா பெர்செக்குட்டுவான் கோலாலம்பூர்",
        "ta_LK": "விலயா பெர்செக்குட்டுவான் கோலாலம்பூர்",
        "ta_MY": "விலயா பெர்செக்குட்டுவான் கோலாலம்பூர்",
        "ta_SG": "விலயா பெர்செக்குட்டுவான் கோலாலம்பூர்",
        "th": "กัวลาลัมเปอร์",
        "th_TH": "กัวลาลัมเปอร์",
        "uk": "Місто Куала-Лумпур",
        "uk_UA": "Місто Куала-Лумпур"
    },
    "15": {
        "en_US": "Wilayah Persekutuan Labuan",
        "be": "Фэдэральная тэрыторыя Лабуан",
        "be_BY": "Фэдэральная тэрыторыя Лабуан",
        "de": "Bundesterritorium Labuan",
        "de_AT": "Bundesterritorium Labuan",
        "de_BE": "Bundesterritorium Labuan",
        "de_CH": "Bundesterritorium Labuan",
        "de_DE": "Bundesterritorium Labuan",
        "de_IT": "Bundesterritorium Labuan",
        "de_LI": "Bundesterritorium Labuan",
        "de_LU": "Bundesterritorium Labuan",
        "eo": "Federacia Teritorio Labuan",
        "eo_001": "Federacia Teritorio Labuan",
        "fr": "Labuan (territoire fédéral)",
        "fr_BE": "Labuan (territoire fédéral)",
        "fr_BF": "Labuan (territoire fédéral)",
        "fr_BI": "Labuan (territoire fédéral)",
        "fr_BJ": "Labuan (territoire fédéral)",
        "fr_BL": "Labuan (territoire fédéral)",
        "fr_CA": "Labuan (territoire fédéral)",
        "fr_CD": "Labuan (territoire fédéral)",
        "fr_CF": "Labuan (territoire fédéral)",
        "fr_CG": "Labuan (territoire fédéral)",
        "fr_CH": "Labuan (territoire fédéral)",
        "fr_CI": "Labuan (territoire fédéral)",
        "fr_CM": "Labuan (territoire fédéral)",
        "fr_DJ": "Labuan (territoire fédéral)",
        "fr_DZ": "Labuan (territoire fédéral)",
        "fr_FR": "Labuan (territoire fédéral)",
        "fr_GA": "Labuan (territoire fédéral)",
        "fr_GF": "Labuan (territoire fédéral)",
        "fr_GN": "Labuan (territoire fédéral)",
        "fr_GP": "Labuan (territoire fédéral)",
        "fr_GQ": "Labuan (territoire fédéral)",
        "fr_HT": "Labuan (territoire fédéral)",
        "fr_KM": "Labuan (territoire fédéral)",
        "fr_LU": "Labuan (territoire fédéral)",
        "fr_MA": "Labuan (territoire fédéral)",
        "fr_MC": "Labuan (territoire fédéral)",
        "fr_MF": "Labuan (territoire fédéral)",
        "fr_MG": "Labuan (territoire fédéral)",
        "fr_ML": "Labuan (territoire fédéral)",
        "fr_MQ": "Labuan (territoire fédéral)",
        "fr_MR": "Labuan (territoire fédéral)",
        "fr_MU": "Labuan (territoire fédéral)",
        "fr_NC": "Labuan (territoire fédéral)",
        "fr_NE": "Labuan (territoire fédéral)",
        "fr_PF": "Labuan (territoire fédéral)",
        "fr_PM": "Labuan (territoire fédéral)",
        "fr_RE": "Labuan (territoire fédéral)",
        "fr_RW": "Labuan (territoire fédéral)",
        "fr_SC": "Labuan (territoire fédéral)",
        "fr_SN": "Labuan (territoire fédéral)",
        "fr_SY": "Labuan (territoire fédéral)",
        "fr_TD": "Labuan (territoire fédéral)",
        "fr_TG": "Labuan (territoire fédéral)",
        "fr_TN": "Labuan (territoire fédéral)",
        "fr_VU": "Labuan (territoire fédéral)",
        "fr_WF": "Labuan (territoire fédéral)",
        "fr_YT": "Labuan (territoire fédéral)",
        "ga": "Críoch Chónaidhme Labuan",
        "ga_GB": "Críoch Chónaidhme Labuan",
        "ga_IE": "Críoch Chónaidhme Labuan",
        "hi": "विलायह पर्सेकुटुआन लाबुआन",
        "hi_IN": "विलायह पर्सेकुटुआन लाबुआन",
        "hu": "Labuan szövetségi terület",
        "hu_HU": "Labuan szövetségi terület",
        "it": "Labuan",
        "it_CH": "Labuan",
        "it_IT": "Labuan",
        "it_SM": "Labuan",
        "it_VA": "Labuan",
        "lt": "Labuano federalinė teritorija",
        "lt_LT": "Labuano federalinė teritorija",
        "nl": "Labuan, Federaal Territorium",
        "nl_AW": "Labuan, Federaal Territorium",
        "nl_BE": "Labuan, Federaal Territorium",
        "nl_BQ": "Labuan, Federaal Territorium",
        "nl_CW": "Labuan, Federaal Territorium",
        "nl_NL": "Labuan, Federaal Territorium",
        "nl_SR": "Labuan, Federaal Territorium",
        "nl_SX": "Labuan, Federaal Territorium",
        "pl": "Labuan (terytorium federalne)",
        "pl_PL": "Labuan (terytorium federalne)",
        "ro": "Teritoriul Federal Labuan",
        "ro_MD": "Teritoriul Federal Labuan",
        "ro_RO": "Teritoriul Federal Labuan",
        "sv": "Labuan (territorium)",
        "sv_AX": "Labuan (territorium)",
        "sv_FI": "Labuan (territorium)",
        "sv_SE": "Labuan (territorium)",
        "ta": "விலயா பெர்செகுடுவான் லாபுவான்",
        "ta_IN": "விலயா பெர்செகுடுவான் லாபுவான்",
        "ta_LK": "விலயா பெர்செகுடுவான் லாபுவான்",
        "ta_MY": "விலயா பெர்செகுடுவான் லாபுவான்",
        "ta_SG": "விலயா பெர்செகுடுவான் லாபுவான்",
        "th": "ลาบวน",
        "th_TH": "ลาบวน",
        "uk": "Місто Лабуан",
        "uk_UA": "Місто Лабуан"
    },
    "16": {
        "en_US": "Wilayah Persekutuan Putrajaya",
        "be": "Фэдэральная тэрыторыя Путраджая",
        "be_BY": "Фэдэральная тэрыторыя Путраджая",
        "de": "Bundesterritorium Putrajaya",
        "de_AT": "Bundesterritorium Putrajaya",
        "de_BE": "Bundesterritorium Putrajaya",
        "de_CH": "Bundesterritorium Putrajaya",
        "de_DE": "Bundesterritorium Putrajaya",
        "de_IT": "Bundesterritorium Putrajaya",
        "de_LI": "Bundesterritorium Putrajaya",
        "de_LU": "Bundesterritorium Putrajaya",
        "eo": "Federacia Teritorio Putrajaya",
        "eo_001": "Federacia Teritorio Putrajaya",
        "fr": "Putrajaya (territoire fédéral)",
        "fr_BE": "Putrajaya (territoire fédéral)",
        "fr_BF": "Putrajaya (territoire fédéral)",
        "fr_BI": "Putrajaya (territoire fédéral)",
        "fr_BJ": "Putrajaya (territoire fédéral)",
        "fr_BL": "Putrajaya (territoire fédéral)",
        "fr_CA": "Putrajaya (territoire fédéral)",
        "fr_CD": "Putrajaya (territoire fédéral)",
        "fr_CF": "Putrajaya (territoire fédéral)",
        "fr_CG": "Putrajaya (territoire fédéral)",
        "fr_CH": "Putrajaya (territoire fédéral)",
        "fr_CI": "Putrajaya (territoire fédéral)",
        "fr_CM": "Putrajaya (territoire fédéral)",
        "fr_DJ": "Putrajaya (territoire fédéral)",
        "fr_DZ": "Putrajaya (territoire fédéral)",
        "fr_FR": "Putrajaya (territoire fédéral)",
        "fr_GA": "Putrajaya (territoire fédéral)",
        "fr_GF": "Putrajaya (territoire fédéral)",
        "fr_GN": "Putrajaya (territoire fédéral)",
        "fr_GP": "Putrajaya (territoire fédéral)",
        "fr_GQ": "Putrajaya (territoire fédéral)",
        "fr_HT": "Putrajaya (territoire fédéral)",
        "fr_KM": "Putrajaya (territoire fédéral)",
        "fr_LU": "Putrajaya (territoire fédéral)",
        "fr_MA": "Putrajaya (territoire fédéral)",
        "fr_MC": "Putrajaya (territoire fédéral)",
        "fr_MF": "Putrajaya (territoire fédéral)",
        "fr_MG": "Putrajaya (territoire fédéral)",
        "fr_ML": "Putrajaya (territoire fédéral)",
        "fr_MQ": "Putrajaya (territoire fédéral)",
        "fr_MR": "Putrajaya (territoire fédéral)",
        "fr_MU": "Putrajaya (territoire fédéral)",
        "fr_NC": "Putrajaya (territoire fédéral)",
        "fr_NE": "Putrajaya (territoire fédéral)",
        "fr_PF": "Putrajaya (territoire fédéral)",
        "fr_PM": "Putrajaya (territoire fédéral)",
        "fr_RE": "Putrajaya (territoire fédéral)",
        "fr_RW": "Putrajaya (territoire fédéral)",
        "fr_SC": "Putrajaya (territoire fédéral)",
        "fr_SN": "Putrajaya (territoire fédéral)",
        "fr_SY": "Putrajaya (territoire fédéral)",
        "fr_TD": "Putrajaya (territoire fédéral)",
        "fr_TG": "Putrajaya (territoire fédéral)",
        "fr_TN": "Putrajaya (territoire fédéral)",
        "fr_VU": "Putrajaya (territoire fédéral)",
        "fr_WF": "Putrajaya (territoire fédéral)",
        "fr_YT": "Putrajaya (territoire fédéral)",
        "ga": "Críoch Chónaidhme Putrajaya",
        "ga_GB": "Críoch Chónaidhme Putrajaya",
        "ga_IE": "Críoch Chónaidhme Putrajaya",
        "hi": "विलायह पर्सेकुटुआन पुत्रजया",
        "hi_IN": "विलायह पर्सेकुटुआन पुत्रजया",
        "hu": "Szövetségi Terület Putrajaya",
        "hu_HU": "Szövetségi Terület Putrajaya",
        "it": "Putrajaya",
        "it_CH": "Putrajaya",
        "it_IT": "Putrajaya",
        "it_SM": "Putrajaya",
        "it_VA": "Putrajaya",
        "lt": "Putradžajos federalinė teritorija",
        "lt_LT": "Putradžajos federalinė teritorija",
        "nl": "Putrajaya, Federaal Territorium",
        "nl_AW": "Putrajaya, Federaal Territorium",
        "nl_BE": "Putrajaya, Federaal Territorium",
        "nl_BQ": "Putrajaya, Federaal Territorium",
        "nl_CW": "Putrajaya, Federaal Territorium",
        "nl_NL": "Putrajaya, Federaal Territorium",
        "nl_SR": "Putrajaya, Federaal Territorium",
        "nl_SX": "Putrajaya, Federaal Territorium",
        "pl": "Putrajaya (terytorium federalne)",
        "pl_PL": "Putrajaya (terytorium federalne)",
        "ro": "Teritoriul Federal Putrajaya",
        "ro_MD": "Teritoriul Federal Putrajaya",
        "ro_RO": "Teritoriul Federal Putrajaya",
        "sv": "Putrajaya (territorium)",
        "sv_AX": "Putrajaya (territorium)",
        "sv_FI": "Putrajaya (territorium)",
        "sv_SE": "Putrajaya (territorium)",
        "ta": "விலயா பெர்செக்குட்டுவான் புத்ராசயா",
        "ta_IN": "விலயா பெர்செக்குட்டுவான் புத்ராசயா",
        "ta_LK": "விலயா பெர்செக்குட்டுவான் புத்ராசயா",
        "ta_MY": "விலயா பெர்செக்குட்டுவான் புத்ராசயா",
        "ta_SG": "விலயா பெர்செக்குட்டுவான் புத்ராசயா",
        "th": "ปุตราจายา",
        "th_TH": "ปุตราจายา",
        "uk": "Місто Путраджая",
        "uk_UA": "Місто Путраджая"
    }
}