{
    "01": {
        "en_US": "Aiwo",
        "be": "Аіва",
        "be_BY": "Аіва",
        "hi": "आइवो",
        "hi_IN": "आइवो",
        "sr": "Ајво",
        "sr@latin": "Ajvo",
        "sr_Cyrl": "Ајво",
        "sr_Cyrl_BA": "Ајво",
        "sr_Cyrl_ME": "Ајво",
        "sr_Cyrl_RS": "Ајво",
        "sr_Cyrl_XK": "Ајво",
        "ta": "ஐவோ",
        "ta_IN": "ஐவோ",
        "ta_LK": "ஐவோ",
        "ta_MY": "ஐவோ",
        "ta_SG": "ஐவோ",
        "uk": "Айво",
        "uk_UA": "Айво"
    },
    "02": {
        "en_US": "Anabar",
        "be": "Анабар",
        "be_BY": "Анабар",
        "hi": "एनाबार",
        "hi_IN": "एनाबार",
        "ja": "アナバル",
        "ja_JP": "アナバル",
        "sr": "Анабар",
        "sr_Cyrl": "Анабар",
        "sr_Cyrl_BA": "Анабар",
        "sr_Cyrl_ME": "Анабар",
        "sr_Cyrl_RS": "Анабар",
        "sr_Cyrl_XK": "Анабар",
        "ta": "அனபார்",
        "ta_IN": "அனபார்",
        "ta_LK": "அனபார்",
        "ta_MY": "அனபார்",
        "ta_SG": "அனபார்",
        "uk": "Анабар",
        "uk_UA": "Анабар"
    },
    "03": {
        "en_US": "Anetan",
        "be": "Анэтан",
        "be_BY": "Анэтан",
        "hi": "ऍनेतन",
        "hi_IN": "ऍनेतन",
        "sr": "Анетан",
        "sr_Cyrl": "Анетан",
        "sr_Cyrl_BA": "Анетан",
        "sr_Cyrl_ME": "Анетан",
        "sr_Cyrl_RS": "Анетан",
        "sr_Cyrl_XK": "Анетан",
        "ta": "அனெட்டன்",
        "ta_IN": "அனெட்டன்",
        "ta_LK": "அனெட்டன்",
        "ta_MY": "அனெட்டன்",
        "ta_SG": "அனெட்டன்",
        "uk": "Анетан",
        "uk_UA": "Анетан"
    },
    "04": {
        "en_US": "Anibare",
        "be": "Анібарэ",
        "be_BY": "Анібарэ",
        "ga": "Anibaré",
        "ga_GB": "Anibaré",
        "ga_IE": "Anibaré",
        "hi": "ऍनिबरे",
        "hi_IN": "ऍनिबरे",
        "ja": "アニバレ",
        "ja_JP": "アニバレ",
        "sr": "Анибаре",
        "sr_Cyrl": "Анибаре",
        "sr_Cyrl_BA": "Анибаре",
        "sr_Cyrl_ME": "Анибаре",
        "sr_Cyrl_RS": "Анибаре",
        "sr_Cyrl_XK": "Анибаре",
        "ta": "அனிபரே",
        "ta_IN": "அனிபரே",
        "ta_LK": "அனிபரே",
        "ta_MY": "அனிபரே",
        "ta_SG": "அனிபரே",
        "uk": "Анібар",
        "uk_UA": "Анібар"
    },
    "05": {
        "en_US": "Baitsi",
        "hi": "बैतसी",
        "hi_IN": "बैतसी",
        "nl": "Baiti",
        "nl_AW": "Baiti",
        "nl_BE": "Baiti",
        "nl_BQ": "Baiti",
        "nl_CW": "Baiti",
        "nl_NL": "Baiti",
        "nl_SR": "Baiti",
        "nl_SX": "Baiti",
        "ta": "பைட்சி",
        "ta_IN": "பைட்சி",
        "ta_LK": "பைட்சி",
        "ta_MY": "பைட்சி",
        "ta_SG": "பைட்சி",
        "uk": "Баїті",
        "uk_UA": "Баїті"
    },
    "06": {
        "en_US": "Boe",
        "be": "Боэ",
        "be_BY": "Боэ",
        "ga": "Bóithrín",
        "ga_GB": "Bóithrín",
        "ga_IE": "Bóithrín",
        "hi": "बोए",
        "hi_IN": "बोए",
        "sr": "Бое",
        "sr_Cyrl": "Бое",
        "sr_Cyrl_BA": "Бое",
        "sr_Cyrl_ME": "Бое",
        "sr_Cyrl_RS": "Бое",
        "sr_Cyrl_XK": "Бое",
        "ta": "போ",
        "ta_IN": "போ",
        "ta_LK": "போ",
        "ta_MY": "போ",
        "ta_SG": "போ",
        "uk": "Бое",
        "uk_UA": "Бое"
    },
    "07": {
        "en_US": "Buada",
        "be": "Буада",
        "be_BY": "Буада",
        "hi": "बुआडा",
        "hi_IN": "बुआडा",
        "sr": "Буада",
        "sr_Cyrl": "Буада",
        "sr_Cyrl_BA": "Буада",
        "sr_Cyrl_ME": "Буада",
        "sr_Cyrl_RS": "Буада",
        "sr_Cyrl_XK": "Буада",
        "uk": "Буада",
        "uk_UA": "Буада"
    },
    "08": {
        "en_US": "Denigomodu",
        "be": "Дэнігамоду",
        "be_BY": "Дэнігамоду",
        "hi": "डेनिगोमोदु",
        "hi_IN": "डेनिगोमोदु",
        "sr": "Денигомоду",
        "sr_Cyrl": "Денигомоду",
        "sr_Cyrl_BA": "Денигомоду",
        "sr_Cyrl_ME": "Денигомоду",
        "sr_Cyrl_RS": "Денигомоду",
        "sr_Cyrl_XK": "Денигомоду",
        "ta": "டெனிகோமோடு",
        "ta_IN": "டெனிகோமோடு",
        "ta_LK": "டெனிகோமோடு",
        "ta_MY": "டெனிகோமோடு",
        "ta_SG": "டெனிகோமோடு",
        "uk": "Денігомоду",
        "uk_UA": "Денігомоду"
    },
    "09": {
        "en_US": "Ewa",
        "be": "Эва",
        "be_BY": "Эва",
        "ga": "Éabha",
        "ga_GB": "Éabha",
        "ga_IE": "Éabha",
        "hi": "इवा",
        "hi_IN": "इवा",
        "ka": "ევა",
        "ka_GE": "ევა",
        "sr": "Ева",
        "sr@latin": "Eva",
        "sr_Cyrl": "Ева",
        "sr_Cyrl_BA": "Ева",
        "sr_Cyrl_ME": "Ева",
        "sr_Cyrl_RS": "Ева",
        "sr_Cyrl_XK": "Ева",
        "ta": "ஈவா",
        "ta_IN": "ஈவா",
        "ta_LK": "ஈவா",
        "ta_MY": "ஈவா",
        "ta_SG": "ஈவா",
        "uk": "Ева",
        "uk_UA": "Ева"
    },
    "10": {
        "en_US": "Ijuw",
        "be": "Іюв",
        "be_BY": "Іюв",
        "ga": "IjuwGeneric",
        "ga_GB": "IjuwGeneric",
        "ga_IE": "IjuwGeneric",
        "hi": "इजुव",
        "hi_IN": "इजुव",
        "uk": "Іюв",
        "uk_UA": "Іюв"
    },
    "11": {
        "en_US": "Meneng",
        "be": "Менэг",
        "be_BY": "Менэг",
        "hi": "मेनेंग",
        "hi_IN": "मेनेंग",
        "sr": "Мененг",
        "sr_Cyrl": "Мененг",
        "sr_Cyrl_BA": "Мененг",
        "sr_Cyrl_ME": "Мененг",
        "sr_Cyrl_RS": "Мененг",
        "sr_Cyrl_XK": "Мененг",
        "ta": "பொருள்",
        "ta_IN": "பொருள்",
        "ta_LK": "பொருள்",
        "ta_MY": "பொருள்",
        "ta_SG": "பொருள்",
        "uk": "Мененг",
        "uk_UA": "Мененг"
    },
    "12": {
        "en_US": "Nibok",
        "be": "Нібок",
        "be_BY": "Нібок",
        "hi": "निबोक",
        "hi_IN": "निबोक",
        "sr": "Нибок",
        "sr_Cyrl": "Нибок",
        "sr_Cyrl_BA": "Нибок",
        "sr_Cyrl_ME": "Нибок",
        "sr_Cyrl_RS": "Нибок",
        "sr_Cyrl_XK": "Нибок",
        "ta": "NIBOK",
        "ta_IN": "NIBOK",
        "ta_LK": "NIBOK",
        "ta_MY": "NIBOK",
        "ta_SG": "NIBOK",
        "uk": "Нібок",
        "uk_UA": "Нібок"
    },
    "13": {
        "en_US": "Uaboe",
        "be": "Уабоэ",
        "be_BY": "Уабоэ",
        "hi": "उआबो",
        "hi_IN": "उआबो",
        "uk": "Уабо",
        "uk_UA": "Уабо"
    },
    "14": {
        "en_US": "Yaren",
        "be": "Ярэн",
        "be_BY": "Ярэн",
        "ga": "An Teanga",
        "ga_GB": "An Teanga",
        "ga_IE": "An Teanga",
        "hi": "यारेन",
        "hi_IN": "यारेन",
        "ja": "ヤレン",
        "ja_JP": "ヤレン",
        "ka": "იარენი",
        "ka_GE": "იარენი",
        "lt": "Jarenas",
        "lt_LT": "Jarenas",
        "sr": "Јарен",
        "sr@latin": "Jaren",
        "sr_Cyrl": "Јарен",
        "sr_Cyrl_BA": "Јарен",
        "sr_Cyrl_ME": "Јарен",
        "sr_Cyrl_RS": "Јарен",
        "sr_Cyrl_XK": "Јарен",
        "ta": "யாரன்",
        "ta_IN": "யாரன்",
        "ta_LK": "யாரன்",
        "ta_MY": "யாரன்",
        "ta_SG": "யாரன்",
        "uk": "Ярен",
        "uk_UA": "Ярен"
    }
}